.DS_Store
noloco/__init__.py
noloco/client.py
noloco/constants.py
noloco/exceptions.py
noloco/fields.py
noloco/mutations.py
noloco/project.py
noloco/queries.py
noloco/requests.py
noloco/results.py
noloco/utils.py
noloco-0.6.1.dist-info/LICENSE
noloco-0.6.1.dist-info/METADATA
noloco-0.6.1.dist-info/WHEEL
noloco-0.6.1.dist-info/top_level.txt
noloco-0.6.1.dist-info/RECORD
