Metadata-Version: 2.1
Name: noloco
Version: 0.6.1
Summary: CRUD operations for Noloco Collections
Home-page: UNKNOWN
Author: Noloco
Author-email: engineering@noloco.io
License: MIT
Platform: UNKNOWN
Requires-Dist: gql[all]
Requires-Dist: pydash
